[{"cost":0.86,"packQuantity":1,"productUid":"toyota-9016040002","shipperId":3,"currencyCode":"USD","maxQuantity":null,"handlingDaysFrom":5,"handlingDaysTo":10,"originalCost":null,"originalCurrencyCode":"USD"},{"cost":0.94,"packQuantity":1,"productUid":"toyota-9018904014","shipperId":3,"currencyCode":"USD","maxQuantity":null,"handlingDaysFrom":5,"handlingDaysTo":10,"originalCost":null,"originalCurrencyCode":"USD"},{"cost":1.27,"packQuantity":1,"productUid":"toyota-9046712008","shipperId":3,"currencyCode":"USD","maxQuantity":null,"handlingDaysFrom":5,"handlingDaysTo":10,"originalCost":null,"originalCurrencyCode":"USD"},{"cost":247.05,"packQuantity":1,"productUid":"toyota-5311190A00","shipperId":2,"currencyCode":"USD","maxQuantity":null,"handlingDaysFrom":5,"handlingDaysTo":7,"originalCost":null,"originalCurrencyCode":"USD"},{"cost":527.05,"packQuantity":1,"productUid":"toyota-5311190A01","shipperId":2,"currencyCode":"USD","maxQuantity":null,"handlingDaysFrom":5,"handlingDaysTo":7,"originalCost":null,"originalCurrencyCode":"USD"},{"cost":46.77,"packQuantity":1,"productUid":"toyota-5313190A00","shipperId":2,"currencyCode":"USD","maxQuantity":null,"handlingDaysFrom":5,"handlingDaysTo":7,"originalCost":null,"originalCurrencyCode":"USD"},{"cost":105.02,"packQuantity":1,"productUid":"toyota-5313190A01","shipperId":2,"currencyCode":"USD","maxQuantity":null,"handlingDaysFrom":5,"handlingDaysTo":7,"originalCost":null,"originalCurrencyCode":"USD"},{"cost":46.77,"packQuantity":1,"productUid":"toyota-5313290A00","shipperId":2,"currencyCode":"USD","maxQuantity":null,"handlingDaysFrom":5,"handlingDaysTo":7,"originalCost":null,"originalCurrencyCode":"USD"},{"cost":105.02,"packQuantity":1,"productUid":"toyota-5313290A01","shipperId":2,"currencyCode":"USD","maxQuantity":null,"handlingDaysFrom":5,"handlingDaysTo":7,"originalCost":null,"originalCurrencyCode":"USD"},{"cost":2,"packQuantity":1,"productUid":"toyota-9016040002","shipperId":2,"currencyCode":"USD","maxQuantity":null,"handlingDaysFrom":5,"handlingDaysTo":7,"originalCost":null,"originalCurrencyCode":"USD"},{"cost":1.83,"packQuantity":1,"productUid":"toyota-9016740010","shipperId":2,"currencyCode":"USD","maxQuantity":null,"handlingDaysFrom":5,"handlingDaysTo":7,"originalCost":null,"originalCurrencyCode":"USD"},{"cost":2.33,"packQuantity":1,"productUid":"toyota-9018304083","shipperId":2,"currencyCode":"USD","maxQuantity":null,"handlingDaysFrom":5,"handlingDaysTo":7,"originalCost":null,"originalCurrencyCode":"USD"},{"cost":1.83,"packQuantity":1,"productUid":"toyota-9018904014","shipperId":2,"currencyCode":"USD","maxQuantity":null,"handlingDaysFrom":5,"handlingDaysTo":7,"originalCost":null,"originalCurrencyCode":"USD"},{"cost":2,"packQuantity":1,"productUid":"toyota-9018904069","shipperId":2,"currencyCode":"USD","maxQuantity":null,"handlingDaysFrom":5,"handlingDaysTo":7,"originalCost":null,"originalCurrencyCode":"USD"},{"cost":2.67,"packQuantity":1,"productUid":"toyota-9046712008","shipperId":2,"currencyCode":"USD","maxQuantity":null,"handlingDaysFrom":5,"handlingDaysTo":7,"originalCost":null,"originalCurrencyCode":"USD"}]