{"manufacturer":"toyota","diagram":{"id":1287978,"globalId":1563209,"slug":"engine_overhaul_gasket_kit","name":"Engine Overhaul Gasket Kit","chapterName":null,"chapterId":null,"position":3,"section":null,"sectionName":null,"hotspots":{"04111":[[366,98,423,115]],"04112":[[361,675,418,691]]},"description":" (8008- )2F","additionalInfo":null,"dateRange":" [08.1980-]","uid":"1563209_3","image":{"originals":"https:\/\/epc.partsbooster.com\/schemas\/toyota\/3ceb7e5f27bdc0ecf4305929c122d58f.png","thumbnails":"https:\/\/epc.partsbooster.com\/schemas\/toyota\/3ceb7e5f27bdc0ecf4305929c122d58f.png"},"imageScaleRatio":1},"diagramsInSection":[{"slug":"engine_overhaul_gasket_kit","uid":"1563209_3","image":{"originals":"https:\/\/epc.partsbooster.com\/schemas\/toyota\/3ceb7e5f27bdc0ecf4305929c122d58f.png","thumbnails":"https:\/\/epc.partsbooster.com\/schemas\/toyota\/3ceb7e5f27bdc0ecf4305929c122d58f.png"},"image_scale_ratio":1}],"variant":{"id":39958,"path":"land_cruiser\/fj60-fj60lv_ka-us-2f-mtm-4f-usa-wgv","parentPath":"land_cruiser","techType":"car","manufacturer":{"slug":"toyota","name":"Toyota"},"generationKey":"land_cruiser-gen_7","header":"Toyota Land Cruiser","subheader":"FJ60","params":[["sales_region",["USA","US"]],["engine",["2F","4200CC"]],["atm_mtm",["MTM","MANUAL TRANSMISSION"]],["gear_shift_type",["4F","MTM, 4-SPEED FLOOR SHIFT"]],["destination",["USA","UNITED STATES OF AMERICA"]],["body",["WGV","STATION WAGON"]],["date_range",["Sep 1986 \u2013 Aug 1987",""]]],"options":[],"vinParams":[]},"countInSection":1,"diagramItems":[{"id":41436328,"refNumber":"04111","qt":1,"itemId":5489736,"description":[["Year",["12.1984-08.1987"]],["Note",["2F..FJ60"]]],"dateRange":"","isSearched":false},{"id":41436329,"refNumber":"04112","qt":1,"itemId":3788110,"description":[["Year",["08.1980-08.1987"]],["Note",["2F..FJ60"]]],"dateRange":"","isSearched":false}],"sectionRefs":null,"products":[{"id":5489736,"number":"0411161060","numberFormatted":"04111-61060","name":"Gasket Kit, Engine Overhaul","slug":"gasket_kit_engine_overhaul","description":"","weight":"1500","hasReplace":false,"isProduced":true,"manufacturer":"toyota","manufacturerName":"Toyota","isLargeItem":false,"articul":null,"supersessions":[{"type":0,"descriptionValueId":0,"supersessionSet":[{"itemId":5521915,"quantity":1}]},{"type":0,"descriptionValueId":0,"supersessionSet":[{"itemId":5684617,"quantity":1}]}],"uid":"toyota-0411161060","guid":"2761F726-1237-11ED-8605-9600009BA0E0","notes":[],"availabilityRate":60},{"id":5521915,"number":"0411161061","numberFormatted":"04111-61061","name":"Gasket Kit, Engine Overha","slug":"new_genuine_part","description":"","weight":"1480","hasReplace":false,"isProduced":true,"manufacturer":"toyota","manufacturerName":"Toyota","isLargeItem":false,"articul":null,"supersessions":[{"type":0,"descriptionValueId":0,"supersessionSet":[{"itemId":5684617,"quantity":1}]}],"uid":"toyota-0411161061","guid":"293565E7-1237-11ED-8605-9600009BA0E0","notes":[],"availabilityRate":null},{"id":5684617,"number":"0411161062","numberFormatted":"04111-61062","name":"Gasket Kit, Engine Overhaul","slug":"new_genuine_part","description":"","weight":"1460","hasReplace":false,"isProduced":true,"manufacturer":"toyota","manufacturerName":"Toyota","isLargeItem":false,"articul":null,"uid":"toyota-0411161062","guid":"2E7949FA-1237-11ED-8605-9600009BA0E0","notes":[],"availabilityRate":null},{"id":3788110,"number":"0411261040","numberFormatted":"04112-61040","name":"Gasket Kit, Engine Valve Grind","slug":"gasket_kit_engine_valve_grind","description":"","weight":"840","hasReplace":false,"isProduced":true,"manufacturer":"toyota","manufacturerName":"Toyota","isLargeItem":false,"articul":null,"supersessions":[{"type":0,"descriptionValueId":0,"supersessionSet":[{"itemId":5685148,"quantity":1}]}],"uid":"toyota-0411261040","guid":"E9DC6E55-1236-11ED-8605-9600009BA0E0","notes":[],"availabilityRate":60},{"id":5685148,"number":"0411261041","numberFormatted":"04112-61041","name":"Gasket Kit Engine","slug":"new_genuine_part","description":"","weight":"740","hasReplace":false,"isProduced":true,"manufacturer":"toyota","manufacturerName":"Toyota","isLargeItem":false,"articul":null,"uid":"toyota-0411261041","guid":"2E7AB821-1237-11ED-8605-9600009BA0E0","notes":[],"availabilityRate":null}],"model":{"id":7068,"path":"land_cruiser","name":"Land Cruiser","techType":"car","manufacturer":{"slug":"toyota","name":"Toyota"},"childrenCount":0,"oneChildPath":"","generationCount":0,"oneGenerationKey":"","notes":[]},"generation":{"techType":"car","manufacturer":{"slug":"toyota","name":"Toyota"},"modelPath":"land_cruiser","key":"land_cruiser-gen_7","image":"land_cruiser\/gen_7","name":"7th Gen","yearRange":"1980 \u2014 1992","variantIds":[],"variantCount":0,"oneVariantPath":"land_cruiser\/fj60-fj60lv_ka-us-2f-mtm-4f-usa-wgv"},"paramNames":{"name":"Name","sales_region":"Sales Region","engine":"Engine","atm_mtm":"Atm,Mtm","gear_shift_type":"Gear Shift Type","destination":"Destination","body":"Body","date_range":"Production Dates"},"seoInfo":{"title":"Engine Overhaul Gasket Kit","subtitle":"Toyota Land Cruiser \u2022 FJ60","welcomeText":[],"footerHeader":"","footerText":[],"metaTitle":"Toyota Land Cruiser FJ60 Engine Overhaul Gasket Kit | YoshiParts","metaDescription":"Shop for Toyota Engine Overhaul Gasket Kit used in Toyota Land Cruiser FJ60 and enjoy worldwide shipping from our authorized dealer. Genuine Toyota parts."},"breadcrumbs":[{"label":"Home","url":"https:\/\/yoshiparts.com\/"},{"label":"Toyota Genuine Parts","url":"https:\/\/yoshiparts.com\/parts\/toyota\/tech"},{"label":"Toyota Car Parts","url":"https:\/\/yoshiparts.com\/parts\/car\/toyota"},{"label":"Toyota Land Cruiser","url":"https:\/\/yoshiparts.com\/parts\/car\/toyota\/land_cruiser"},{"label":"7th Gen","url":"https:\/\/yoshiparts.com\/parts\/car\/toyota\/land_cruiser\/params\/land_cruiser-gen_7\/one"},{"label":"FJ60","url":"https:\/\/yoshiparts.com\/parts\/car\/toyota\/diagrams\/land_cruiser\/fj60-fj60lv_ka-us-2f-mtm-4f-usa-wgv"},{"label":"Toyota Land Cruiser FJ60 Engine Overhaul Gasket Kit","url":"https:\/\/yoshiparts.com\/parts\/car\/toyota\/products\/land_cruiser\/fj60-fj60lv_ka-us-2f-mtm-4f-usa-wgv\/1563209_3"}],"jsonld":[{"@context":"http:\/\/schema.org","@type":"BreadcrumbList","itemListElement":[{"@type":"ListItem","position":1,"item":{"@id":"https:\/\/yoshiparts.com\/","name":"Home"}},{"@type":"ListItem","position":2,"item":{"@id":"https:\/\/yoshiparts.com\/parts\/toyota\/tech","name":"Toyota Genuine Parts"}},{"@type":"ListItem","position":3,"item":{"@id":"https:\/\/yoshiparts.com\/parts\/car\/toyota","name":"Toyota Car Parts"}},{"@type":"ListItem","position":4,"item":{"@id":"https:\/\/yoshiparts.com\/parts\/car\/toyota\/land_cruiser","name":"Toyota Land Cruiser"}},{"@type":"ListItem","position":5,"item":{"@id":"https:\/\/yoshiparts.com\/parts\/car\/toyota\/land_cruiser\/params\/land_cruiser-gen_7\/one","name":"7th Gen"}},{"@type":"ListItem","position":6,"item":{"@id":"https:\/\/yoshiparts.com\/parts\/car\/toyota\/diagrams\/land_cruiser\/fj60-fj60lv_ka-us-2f-mtm-4f-usa-wgv","name":"FJ60"}},{"@type":"ListItem","position":7,"item":{"@id":"https:\/\/yoshiparts.com\/parts\/car\/toyota\/products\/land_cruiser\/fj60-fj60lv_ka-us-2f-mtm-4f-usa-wgv\/1563209_3","name":"Toyota Land Cruiser FJ60 Engine Overhaul Gasket Kit"}}]}]}