{"manufacturer":"toyota","diagram":{"id":1287988,"globalId":1726002,"slug":"radiator_water_outlet","name":"Radiator & Water Outlet","chapterName":null,"chapterId":null,"position":15,"section":null,"sectionName":null,"hotspots":{"1605":[[820,902,870,919]],"16261":[[1318,265,1370,282]],"16261A":[[1391,265,1462,282],[1336,458,1407,475]],"16331":[[1546,373,1598,390]],"16331A":[[1312,509,1386,527]],"16333":[[1469,743,1524,761]],"16341":[[1318,571,1371,588]],"16343":[[1537,701,1592,718]],"16346":[[1532,434,1587,451]],"16361":[[415,162,467,179],[710,825,765,842]],"16362":[[824,43,879,61]],"16362A":[[1261,154,1332,171]],"16363":[[771,96,826,113]],"16381":[[1229,471,1282,488],[990,708,1043,725]],"16381B":[[984,557,1052,574]],"16381C":[[1239,425,1309,442]],"16400":[[164,1009,220,1027]],"16400B":[[247,959,315,977]],"16400F":[[166,960,233,977]],"16401":[[69,960,122,977]],"16470":[[283,387,339,404]],"16470A":[[146,87,216,104]],"16470B":[[55,86,122,104],[233,88,301,105]],"16470C":[[13,260,81,277]],"16471":[[198,39,250,56]],"16472":[[331,87,387,104]],"16507B":[[1222,1045,1291,1063]],"16571":[[881,557,934,574]],"16571A":[[771,382,841,399],[749,431,818,448]],"16572":[[1180,625,1236,642],[848,1001,903,1018]],"16572A":[[943,949,1013,967],[782,1036,853,1053]],"16572C":[[1258,761,1326,778],[1162,770,1230,787]],"16577":[[1099,813,1154,830],[1365,1007,1421,1024]],"16582":[[302,1049,391,1067]],"16583":[[302,1066,390,1083]],"16584":[[690,1055,745,1072]],"16584A":[[690,1012,761,1030]],"16585":[[339,965,429,982]],"16586":[[339,981,428,998]],"16701":[[382,438,435,455]],"9010908038":[[978,483,1080,498]],"9011908264":[[992,325,1094,340]],"9011908344":[[1101,576,1203,591]],"9017906158":[[467,412,594,430]],"9017908146":[[1235,892,1336,908],[621,934,748,950]],"9020108135":[[1040,457,1142,472]],"9046709022":[[60,219,183,236]],"9161160845":[[1463,216,1590,231]],"9161161020":[[994,517,1096,532]],"9161161025":[[1314,730,1441,745]],"9165140614":[[1327,80,1455,94],[139,383,266,399]],"9165140816":[[644,859,771,874],[256,1016,383,1031]],"9165160614":[[666,61,794,76]],"9165160620":[[954,101,1057,116]],"9165160830":[[29,435,157,450]],"9165160840":[[655,966,757,981]],"9453100800":[[977,395,1079,411]]},"description":" (8008- )2F","additionalInfo":null,"dateRange":" [08.1980-]","uid":"1726002_15","image":{"originals":"https:\/\/epc.partsbooster.com\/schemas\/toyota\/02064bee4412b58016a7ad8c2695068d.png","thumbnails":"https:\/\/epc.partsbooster.com\/schemas\/toyota\/02064bee4412b58016a7ad8c2695068d.png"},"imageScaleRatio":1},"diagramsInSection":[{"slug":"radiator_water_outlet","uid":"1726002_15","image":{"originals":"https:\/\/epc.partsbooster.com\/schemas\/toyota\/02064bee4412b58016a7ad8c2695068d.png","thumbnails":"https:\/\/epc.partsbooster.com\/schemas\/toyota\/02064bee4412b58016a7ad8c2695068d.png"},"image_scale_ratio":1}],"variant":{"id":39958,"path":"land_cruiser\/fj60-fj60lv_ka-us-2f-mtm-4f-usa-wgv","parentPath":"land_cruiser","techType":"car","manufacturer":{"slug":"toyota","name":"Toyota"},"generationKey":"land_cruiser-gen_7","header":"Toyota Land Cruiser","subheader":"FJ60","params":[["sales_region",["USA","US"]],["engine",["2F","4200CC"]],["atm_mtm",["MTM","MANUAL TRANSMISSION"]],["gear_shift_type",["4F","MTM, 4-SPEED FLOOR SHIFT"]],["destination",["USA","UNITED STATES OF AMERICA"]],["body",["WGV","STATION WAGON"]],["date_range",["Sep 1986 \u2013 Aug 1987",""]]],"options":[],"vinParams":[]},"countInSection":1,"diagramItems":[{"id":41436558,"refNumber":"16261","qt":1,"itemId":3788422,"description":[["Year",["08.1980-08.1987"]],["Note",["2F..FJ60"]]],"dateRange":"","isSearched":false},{"id":41436559,"refNumber":"16261A","qt":2,"itemId":3625581,"description":[["Year",["08.1980-08.1987"]],["Note",["2F..FJ60"]],["Required",["2 pcs"]]],"dateRange":"","isSearched":false},{"id":41436560,"refNumber":"16331","qt":1,"itemId":3788429,"description":[["Year",["08.1980-08.1987"]],["Note",["2F..FJ60..USA"]]],"dateRange":"","isSearched":false},{"id":41436561,"refNumber":"16331A","qt":1,"itemId":3788431,"description":[["Year",["11.1984-08.1987"]],["Note",["2F..FJ60","*WAX 88-100"]]],"dateRange":"","isSearched":false},{"id":41436562,"refNumber":"16333","qt":1,"itemId":3788432,"description":[["Year",["08.1980-08.1987"]],["Note",["2F..FJ60..USA"]]],"dateRange":"","isSearched":false},{"id":41436563,"refNumber":"16341","qt":1,"itemId":3788435,"description":[["Year",["08.1980-08.1987"]],["Note",["2F..FJ60"]]],"dateRange":"","isSearched":false},{"id":41436564,"refNumber":"16343","qt":1,"itemId":3788437,"description":[["Year",["11.1984-08.1987"]],["Note",["2F..FJ60"]]],"dateRange":"","isSearched":false},{"id":41436565,"refNumber":"16346","qt":1,"itemId":3788438,"description":[["Year",["08.1980-08.1987"]],["Note",["2F..FJ60"]]],"dateRange":"","isSearched":false},{"id":41436566,"refNumber":"16361","qt":1,"itemId":3788442,"description":[["Year",["08.1980-08.1987"]],["Note",["2F..FJ60..USA"]]],"dateRange":"","isSearched":false},{"id":41436567,"refNumber":"16362","qt":1,"itemId":3867658,"description":[["Year",["08.1980-08.1987"]],["Note",["2F..FJ60..USA"]]],"dateRange":"","isSearched":false},{"id":41436568,"refNumber":"16362A","qt":1,"itemId":3868024,"description":[["Year",["03.1986-08.1987"]],["Note",["2F..FJ60"]]],"dateRange":"","isSearched":false},{"id":41436569,"refNumber":"16363","qt":1,"itemId":3857598,"description":[["Year",["08.1980-08.1987"]],["Note",["2F..FJ60..USA"]]],"dateRange":"","isSearched":false},{"id":41436570,"refNumber":"16381","qt":1,"itemId":3788459,"description":[["Year",["08.1980-08.1987"]],["Note",["2F..FJ60..USA"]]],"dateRange":"","isSearched":false},{"id":41436571,"refNumber":"16381C","qt":1,"itemId":3788463,"description":[["Year",["08.1980-08.1987"]],["Note",["2F..FJ60..USA"]]],"dateRange":"","isSearched":false},{"id":41436572,"refNumber":"16400","qt":1,"itemId":5489751,"description":[["Year",["04.1986-08.1987"]],["Note",["2F..FJ60"]]],"dateRange":"","isSearched":false},{"id":41436573,"refNumber":"16400B","qt":1,"itemId":3544827,"description":[["Year",["08.1980-08.1987"]],["Note",["2F..FJ60"]]],"dateRange":"","isSearched":false},{"id":41436574,"refNumber":"16400F","qt":1,"itemId":2934529,"description":[["Year",["08.1980-08.1987"]],["Note",["2F..FJ60"]]],"dateRange":"","isSearched":false},{"id":41436575,"refNumber":"16401","qt":1,"itemId":3010768,"description":[["Year",["04.1986-08.1987"]],["Note",["2F..FJ60"]]],"dateRange":"","isSearched":false},{"id":41436576,"refNumber":"16470","qt":1,"itemId":3848465,"description":[["Year",["08.1980-08.1987"]],["Note",["2F..FJ60"]]],"dateRange":"","isSearched":false},{"id":41436577,"refNumber":"16470A","qt":1,"itemId":3848466,"description":[["Year",["08.1980-08.1987"]],["Note",["2F..FJ60","*H,L=670"]]],"dateRange":"","isSearched":false},{"id":41436578,"refNumber":"16470B","qt":2,"itemId":2816581,"description":[["Year",["08.1980-08.1987"]],["Note",["2F..FJ60"]],["Required",["2 pcs"]]],"dateRange":"","isSearched":false},{"id":41436579,"refNumber":"16470C","qt":1,"itemId":3848467,"description":[["Year",["08.1980-08.1987"]],["Note",["2F..FJ60"]]],"dateRange":"","isSearched":false},{"id":41436580,"refNumber":"16471","qt":1,"itemId":3848469,"description":[["Year",["08.1980-08.1987"]],["Note",["2F..FJ60"]]],"dateRange":"","isSearched":false},{"id":41436581,"refNumber":"16472","qt":1,"itemId":3339952,"description":[["Year",["08.1980-08.1987"]],["Note",["2F..FJ60"]]],"dateRange":"","isSearched":false},{"id":41436582,"refNumber":"16507B","qt":1,"itemId":3153015,"description":[["Year",["08.1980-08.1987"]],["Note",["2F..FJ60..USA","W\/COOLER"]]],"dateRange":"","isSearched":false},{"id":41436583,"refNumber":"16571","qt":1,"itemId":3848474,"description":[["Year",["08.1980-08.1987"]],["Note",["2F..FJ60"]]],"dateRange":"","isSearched":false},{"id":41436584,"refNumber":"16571A","qt":2,"itemId":3572394,"description":[["Year",["08.1980-08.1987"]],["Note",["2F..FJ60"]],["Required",["2 pcs"]]],"dateRange":"","isSearched":false},{"id":41436585,"refNumber":"16572","qt":1,"itemId":3788493,"description":[["Year",["08.1980-08.1987"]],["Note",["2F..FJ60..USA","WATER PUMP SIDE,W\/COOLER"]]],"dateRange":"","isSearched":false},{"id":41436586,"refNumber":"16572","qt":1,"itemId":3848479,"description":[["Year",["08.1980-08.1987"]],["Note",["2F..FJ60..USA","RADIATOR SIDE,W\/COOLER"]]],"dateRange":"","isSearched":false},{"id":41436587,"refNumber":"16572A","qt":2,"itemId":3753175,"description":[["Year",["10.1980-08.1987"]],["Note",["2F..FJ60..USA","W\/COOLER"]],["Required",["2 pcs"]]],"dateRange":"","isSearched":false},{"id":41436588,"refNumber":"16572C","qt":2,"itemId":2835170,"description":[["Year",["08.1980-08.1987"]],["Note",["2F..FJ60"]],["Required",["2 pcs"]]],"dateRange":"","isSearched":false},{"id":41436589,"refNumber":"16577","qt":1,"itemId":3788500,"description":[["Year",["08.1980-08.1987"]],["Note",["2F..FJ60..USA","W\/COOLER"]]],"dateRange":"","isSearched":false},{"id":41436590,"refNumber":"16582","qt":1,"itemId":3848485,"description":[["Year",["08.1980-08.1987"]],["Note",["2F..FJ60"]]],"dateRange":"","isSearched":false},{"id":41436591,"refNumber":"16583","qt":1,"itemId":3848486,"description":[["Year",["08.1980-08.1987"]],["Note",["2F..FJ60"]]],"dateRange":"","isSearched":false},{"id":41436592,"refNumber":"16584","qt":2,"itemId":3848487,"description":[["Year",["08.1980-08.1987"]],["Note",["2F..FJ60"]],["Required",["2 pcs"]]],"dateRange":"","isSearched":false},{"id":41436593,"refNumber":"16584A","qt":2,"itemId":3848488,"description":[["Year",["08.1980-08.1987"]],["Note",["2F..FJ60"]],["Required",["2 pcs"]]],"dateRange":"","isSearched":false},{"id":41436594,"refNumber":"16585","qt":1,"itemId":3848489,"description":[["Year",["08.1980-08.1987"]],["Note",["2F..FJ60"]]],"dateRange":"","isSearched":false},{"id":41436595,"refNumber":"16586","qt":1,"itemId":3848490,"description":[["Year",["08.1980-08.1987"]],["Note",["2F..FJ60"]]],"dateRange":"","isSearched":false},{"id":41436596,"refNumber":"16701","qt":1,"itemId":5232907,"description":[["Year",["08.1980-08.1987"]],["Note",["2F..FJ60..USA"]]],"dateRange":"","isSearched":false},{"id":41436597,"refNumber":"9010908038","qt":1,"itemId":6002574,"description":[],"dateRange":"","isSearched":false},{"id":41436598,"refNumber":"9011908264","qt":1,"itemId":5954371,"description":[],"dateRange":"","isSearched":false},{"id":41436599,"refNumber":"9011908344","qt":1,"itemId":5954400,"description":[],"dateRange":"","isSearched":false},{"id":41436600,"refNumber":"9017906158","qt":1,"itemId":2822256,"description":[],"dateRange":"","isSearched":false},{"id":41436601,"refNumber":"9017908146","qt":1,"itemId":3705415,"description":[],"dateRange":"","isSearched":false},{"id":41436602,"refNumber":"9020108135","qt":1,"itemId":3545283,"description":[],"dateRange":"","isSearched":false},{"id":41436603,"refNumber":"9046709022","qt":1,"itemId":5964545,"description":[],"dateRange":"","isSearched":false},{"id":41436604,"refNumber":"9161160845","qt":1,"itemId":5670922,"description":[],"dateRange":"","isSearched":false},{"id":41436605,"refNumber":"9161161020","qt":1,"itemId":2924613,"description":[],"dateRange":"","isSearched":false},{"id":41436606,"refNumber":"9161161025","qt":1,"itemId":2835914,"description":[],"dateRange":"","isSearched":false},{"id":41436607,"refNumber":"9165140614","qt":1,"itemId":5806477,"description":[],"dateRange":"","isSearched":false},{"id":41436608,"refNumber":"9165140816","qt":1,"itemId":5806485,"description":[],"dateRange":"","isSearched":false},{"id":41436609,"refNumber":"9165160614","qt":1,"itemId":3120336,"description":[],"dateRange":"","isSearched":false},{"id":41436610,"refNumber":"9165160620","qt":1,"itemId":5806495,"description":[],"dateRange":"","isSearched":false},{"id":41436611,"refNumber":"9165160830","qt":1,"itemId":3794259,"description":[],"dateRange":"","isSearched":false},{"id":41436612,"refNumber":"9165160840","qt":1,"itemId":5806505,"description":[],"dateRange":"","isSearched":false},{"id":41436613,"refNumber":"9453100800","qt":1,"itemId":3862781,"description":[],"dateRange":"","isSearched":false}],"sectionRefs":{"1605":{"id":1287989,"globalId":1843409,"slug":"v_belt","name":"V-Belt","chapterName":null,"position":16,"section":null,"chapterId":null,"image":null,"imageScaleRatio":null,"hotspots":null,"description":"","dateRange":"","uid":"1843409_16","refNumber":null}},"products":[{"id":3788422,"number":"1626160011","numberFormatted":"16261-60011","name":"Hose, Water By-Pass","slug":"hose_water_by_pass","description":"","weight":"60","hasReplace":false,"isProduced":true,"manufacturer":"toyota","manufacturerName":"Toyota","isLargeItem":false,"articul":null,"uid":"toyota-1626160011","guid":"E9DD7111-1236-11ED-8605-9600009BA0E0","notes":[],"availabilityRate":60},{"id":3788432,"number":"1633161032","numberFormatted":"16331-61032","name":"Housing, Water Outlet","slug":"housing_water_outlet","description":"","weight":"390","hasReplace":false,"isProduced":true,"manufacturer":"toyota","manufacturerName":"Toyota","isLargeItem":false,"articul":null,"uid":"toyota-1633161032","guid":"E9DD7402-1236-11ED-8605-9600009BA0E0","notes":[],"availabilityRate":60},{"id":3788429,"number":"1633361110","numberFormatted":"16333-61110","name":"Outlet, Water","slug":"outlet_water","description":"","weight":"470","hasReplace":false,"isProduced":true,"manufacturer":"toyota","manufacturerName":"Toyota","isLargeItem":false,"articul":null,"uid":"toyota-1633361110","guid":"7AFD637B-DB1E-4F27-A221-C866C9EA0245","notes":[],"availabilityRate":60},{"id":3788435,"number":"1634161020","numberFormatted":"16341-61020","name":"Gasket, Water Outlet","slug":"gasket_water_outlet","description":"","weight":"3","hasReplace":false,"isProduced":true,"manufacturer":"toyota","manufacturerName":"Toyota","isLargeItem":false,"articul":null,"supersessions":[{"type":0,"descriptionValueId":0,"supersessionSet":[{"itemId":3857590,"quantity":1}]}],"uid":"toyota-1634161020","guid":"E9DD74C4-1236-11ED-8605-9600009BA0E0","notes":[],"availabilityRate":60},{"id":3857590,"number":"1634161030","numberFormatted":"16341-61030","name":"Gasket, Water Outlet","slug":"gasket_water_outlet","description":"","weight":"5","hasReplace":false,"isProduced":true,"manufacturer":"toyota","manufacturerName":"Toyota","isLargeItem":false,"articul":null,"uid":"toyota-1634161030","guid":"7A622E30-9C3A-4D49-8934-9080D1ECCEFF","notes":[],"availabilityRate":60},{"id":3788437,"number":"1634361010","numberFormatted":"16343-61010","name":"Gasket, Water Outlet Housing","slug":"gasket_water_outlet_housing","description":"","weight":"3","hasReplace":false,"isProduced":true,"manufacturer":"toyota","manufacturerName":"Toyota","isLargeItem":false,"articul":null,"supersessions":[{"type":0,"descriptionValueId":0,"supersessionSet":[{"itemId":3857592,"quantity":1}]}],"uid":"toyota-1634361010","guid":"E9DD7578-1236-11ED-8605-9600009BA0E0","notes":[],"availabilityRate":60},{"id":3857592,"number":"1634361020","numberFormatted":"16343-61020","name":"Gasket, Water Outlet Housing","slug":"gasket_water_outlet_housing","description":"","weight":"4","hasReplace":false,"isProduced":true,"manufacturer":"toyota","manufacturerName":"Toyota","isLargeItem":false,"articul":null,"uid":"toyota-1634361020","guid":"ED2B2392-1236-11ED-8605-9600009BA0E0","notes":[],"availabilityRate":60},{"id":3867658,"number":"1636061015","numberFormatted":"16360-61015","name":"Fan, No.2","slug":"fan_no_2","description":"","weight":"2390","hasReplace":false,"isProduced":true,"manufacturer":"toyota","manufacturerName":"Toyota","isLargeItem":false,"articul":null,"uid":"toyota-1636061015","guid":"ED6229BE-1236-11ED-8605-9600009BA0E0","notes":[],"availabilityRate":60},{"id":3788442,"number":"1636161020","numberFormatted":"16361-61020","name":"Fan","slug":"fan","description":"","weight":"880","hasReplace":false,"isProduced":true,"manufacturer":"toyota","manufacturerName":"Toyota","isLargeItem":false,"articul":null,"uid":"toyota-1636161020","guid":"E9DD76EE-1236-11ED-8605-9600009BA0E0","notes":[],"availabilityRate":60},{"id":3857598,"number":"1636361020","numberFormatted":"16363-61020","name":"Motor, Cooling Fan","slug":"motor_cooling_fan","description":"","weight":"700","hasReplace":false,"isProduced":true,"manufacturer":"toyota","manufacturerName":"Toyota","isLargeItem":false,"articul":null,"uid":"toyota-1636361020","guid":"ED2B2557-1236-11ED-8605-9600009BA0E0","notes":[],"availabilityRate":60},{"id":3788459,"number":"1638161011","numberFormatted":"16381-61011","name":"Bar, Fan Belt Adjusting","slug":"bar_fan_belt_adjusting","description":"","weight":"330","hasReplace":false,"isProduced":true,"manufacturer":"toyota","manufacturerName":"Toyota","isLargeItem":false,"articul":null,"uid":"toyota-1638161011","guid":"E9DD940E-1236-11ED-8605-9600009BA0E0","notes":[],"availabilityRate":60},{"id":5489751,"number":"1640061051","numberFormatted":"16400-61051","name":"Radiator Assy","slug":"radiator_assy","description":"","weight":"12500","hasReplace":false,"isProduced":true,"manufacturer":"toyota","manufacturerName":"Toyota","isLargeItem":false,"articul":null,"uid":"toyota-1640061051","guid":"2762059C-1237-11ED-8605-9600009BA0E0","notes":[],"availabilityRate":60},{"id":3697485,"number":"1640154750","numberFormatted":"16401-54750","name":"Cap Sub-Assy, Radiator","slug":"cap_sub_assy_radiator","description":"","weight":"40","hasReplace":false,"isProduced":true,"manufacturer":"toyota","manufacturerName":"Toyota","isLargeItem":false,"articul":null,"uid":"toyota-1640154750","guid":"039680EA-8008-45AF-A1B0-A5EF6D389B1B","notes":[],"availabilityRate":99},{"id":3010768,"number":"1640171010","numberFormatted":"16401-71010","name":"Cap Sub-Assy, Radiator","slug":"cap_sub_assy_radiator","description":"","weight":"47","hasReplace":false,"isProduced":true,"manufacturer":"toyota","manufacturerName":"Toyota","isLargeItem":false,"articul":null,"supersessions":[{"type":0,"descriptionValueId":0,"supersessionSet":[{"itemId":3697485,"quantity":1}]}],"uid":"toyota-1640171010","guid":"20CEE065-6FCD-4A88-BC6F-81BE53DF97DD","notes":[],"availabilityRate":99},{"id":3848469,"number":"1640590A00","numberFormatted":"16405-90A00","name":"Cap Sub-Assy, Reserve Tank","slug":"cap_sub_assy_reserve_tank","description":"","weight":"110","hasReplace":false,"isProduced":true,"manufacturer":"toyota","manufacturerName":"Toyota","isLargeItem":false,"articul":null,"supersessions":[{"type":0,"descriptionValueId":0,"supersessionSet":[{"itemId":5232900,"quantity":1}]}],"uid":"toyota-1640590A00","guid":"EC8EA7AB-1236-11ED-8605-9600009BA0E0","notes":[],"availabilityRate":60},{"id":5232900,"number":"1640590A03","numberFormatted":"16405-90A03","name":"Cap Sub-Assy, Reserve Tank","slug":"cap_sub_assy_reserve_tank","description":"","weight":"110","hasReplace":false,"isProduced":true,"manufacturer":"toyota","manufacturerName":"Toyota","isLargeItem":false,"articul":null,"uid":"toyota-1640590A03","guid":"1FD6F889-1237-11ED-8605-9600009BA0E0","notes":[],"availabilityRate":60},{"id":3544827,"number":"1641724200","numberFormatted":"16417-24200","name":"Plug, Radiator Drain Cock","slug":"plug_radiator_drain_cock","description":"","weight":"5","hasReplace":false,"isProduced":true,"manufacturer":"toyota","manufacturerName":"Toyota","isLargeItem":false,"articul":null,"uid":"toyota-1641724200","guid":"92E6A235-2C94-4AB7-B44D-C3220B9683C3","notes":[],"availabilityRate":99},{"id":2934529,"number":"1641824200","numberFormatted":"16418-24200","name":"Packing(For Radiator Drain Cock)","slug":"packing_for_radiator_drain_cock","description":"","weight":"3","hasReplace":false,"isProduced":true,"manufacturer":"toyota","manufacturerName":"Toyota","isLargeItem":false,"articul":null,"uid":"toyota-1641824200","guid":"17F047E6-4D9D-4374-BFA6-E0969FA95498","notes":[],"availabilityRate":99},{"id":3848465,"number":"1648090A00","numberFormatted":"16480-90A00","name":"Tank Assy, Radiator Reserve","slug":"tank_assy_radiator_reserve","description":"","weight":"310","hasReplace":false,"isProduced":true,"manufacturer":"toyota","manufacturerName":"Toyota","isLargeItem":false,"articul":null,"uid":"toyota-1648090A00","guid":"EC8EA62D-1236-11ED-8605-9600009BA0E0","notes":[],"availabilityRate":60},{"id":3788500,"number":"1657761120","numberFormatted":"16577-61120","name":"Pipe, Radiator, No.7","slug":"pipe_radiator_no_7","description":"","weight":"470","hasReplace":false,"isProduced":true,"manufacturer":"toyota","manufacturerName":"Toyota","isLargeItem":false,"articul":null,"uid":"toyota-1657761120","guid":"E9DDC363-1236-11ED-8605-9600009BA0E0","notes":[],"availabilityRate":60},{"id":3848485,"number":"1658261010","numberFormatted":"16582-61010","name":"Bracket, Radiator, No.1","slug":"bracket_radiator_no_1","description":"","weight":"200","hasReplace":false,"isProduced":true,"manufacturer":"toyota","manufacturerName":"Toyota","isLargeItem":false,"articul":null,"uid":"toyota-1658261010","guid":"EC8EAD8F-1236-11ED-8605-9600009BA0E0","notes":[],"availabilityRate":60},{"id":3848486,"number":"1658361010","numberFormatted":"16583-61010","name":"Bracket, Radiator, No.2","slug":"bracket_radiator_no_2","description":"","weight":"200","hasReplace":false,"isProduced":true,"manufacturer":"toyota","manufacturerName":"Toyota","isLargeItem":false,"articul":null,"uid":"toyota-1658361010","guid":"EC8EADEE-1236-11ED-8605-9600009BA0E0","notes":[],"availabilityRate":60},{"id":3848487,"number":"1658461010","numberFormatted":"16584-61010","name":"Insulator, Radiator Mounting","slug":"insulator_radiator_mounting","description":"","weight":"44","hasReplace":false,"isProduced":true,"manufacturer":"toyota","manufacturerName":"Toyota","isLargeItem":false,"articul":null,"uid":"toyota-1658461010","guid":"EC8EAE59-1236-11ED-8605-9600009BA0E0","notes":[],"availabilityRate":60},{"id":3848489,"number":"1658561010","numberFormatted":"16585-61010","name":"Bracket, Radiator, No.3","slug":"bracket_radiator_no_3","description":"","weight":"130","hasReplace":false,"isProduced":true,"manufacturer":"toyota","manufacturerName":"Toyota","isLargeItem":false,"articul":null,"uid":"toyota-1658561010","guid":"EC8EAFA9-1236-11ED-8605-9600009BA0E0","notes":[],"availabilityRate":60},{"id":3848490,"number":"1658661010","numberFormatted":"16586-61010","name":"Bracket, Radiator, No.4","slug":"bracket_radiator_no_4","description":"","weight":"130","hasReplace":false,"isProduced":true,"manufacturer":"toyota","manufacturerName":"Toyota","isLargeItem":false,"articul":null,"uid":"toyota-1658661010","guid":"EC8EB1FF-1236-11ED-8605-9600009BA0E0","notes":[],"availabilityRate":60},{"id":5232907,"number":"1671161151","numberFormatted":"16711-61151","name":"Shroud Sub-Assy, Fan","slug":"shroud_sub_assy_fan","description":"","weight":"2000","hasReplace":false,"isProduced":true,"manufacturer":"toyota","manufacturerName":"Toyota","isLargeItem":false,"articul":null,"uid":"toyota-1671161151","guid":"1FD70438-1237-11ED-8605-9600009BA0E0","notes":[],"availabilityRate":60},{"id":3788463,"number":"1731761020","numberFormatted":"17317-61020","name":"Bar, Fan Belt Adjusting, No.2","slug":"bar_fan_belt_adjusting_no_2","description":"","weight":"30","hasReplace":false,"isProduced":true,"manufacturer":"toyota","manufacturerName":"Toyota","isLargeItem":false,"articul":null,"uid":"toyota-1731761020","guid":"E9DD9839-1236-11ED-8605-9600009BA0E0","notes":[],"availabilityRate":60},{"id":3153015,"number":"1785338010","numberFormatted":"17853-38010","name":"Insulator, Air Cleaner Bracket","slug":"insulator_air_cleaner_bracket","description":"","weight":"45","hasReplace":false,"isProduced":true,"manufacturer":"toyota","manufacturerName":"Toyota","isLargeItem":false,"articul":null,"uid":"toyota-1785338010","guid":"D3B98B19-1236-11ED-8605-9600009BA0E0","notes":[],"availabilityRate":60},{"id":3868024,"number":"5380990A00","numberFormatted":"53809-90A00","name":"Duct Sub-Assy, Cooling Fan Air","slug":"duct_sub_assy_cooling_fan_air","description":"","weight":"330","hasReplace":false,"isProduced":true,"manufacturer":"toyota","manufacturerName":"Toyota","isLargeItem":false,"articul":null,"uid":"toyota-5380990A00","guid":"ED635F1B-1236-11ED-8605-9600009BA0E0","notes":[],"availabilityRate":60},{"id":3339952,"number":"8533822020","numberFormatted":"85338-22020","name":"Hose, Breather","slug":"hose_breather","description":"","weight":"12","hasReplace":false,"isProduced":true,"manufacturer":"toyota","manufacturerName":"Toyota","isLargeItem":false,"articul":null,"uid":"toyota-8533822020","guid":"D9FF712B-1236-11ED-8605-9600009BA0E0","notes":[],"availabilityRate":99},{"id":3848467,"number":"8536130070","numberFormatted":"85361-30070","name":"Bracket(For Radiator Reserve Tank)","slug":"bracket_for_radiator_reserve_tank","description":"","weight":"120","hasReplace":false,"isProduced":true,"manufacturer":"toyota","manufacturerName":"Toyota","isLargeItem":false,"articul":null,"uid":"toyota-8536130070","guid":"EC8EA6EF-1236-11ED-8605-9600009BA0E0","notes":[],"availabilityRate":60},{"id":6002574,"number":"9010908038","numberFormatted":"90109-08038","name":"New Genuine Part","slug":"new_genuine_part","description":"","weight":"10","hasReplace":false,"isProduced":true,"manufacturer":"toyota","manufacturerName":"Toyota","isLargeItem":false,"articul":null,"uid":"toyota-9010908038","guid":"395B8EE3-1237-11ED-8605-9600009BA0E0","notes":[],"availabilityRate":60},{"id":5954371,"number":"9011908264","numberFormatted":"90119-08264","name":"Washer-Bolt","slug":"new_genuine_part","description":"","weight":"40","hasReplace":false,"isProduced":true,"manufacturer":"toyota","manufacturerName":"Toyota","isLargeItem":false,"articul":null,"uid":"toyota-9011908264","guid":"374AE92A-1237-11ED-8605-9600009BA0E0","notes":[],"availabilityRate":99},{"id":5954400,"number":"9011908344","numberFormatted":"90119-08344","name":"Bolt","slug":"new_genuine_part","description":"","weight":"30","hasReplace":false,"isProduced":true,"manufacturer":"toyota","manufacturerName":"Toyota","isLargeItem":false,"articul":null,"uid":"toyota-9011908344","guid":"374AFCCC-1237-11ED-8605-9600009BA0E0","notes":[],"availabilityRate":60},{"id":2822256,"number":"9017906158","numberFormatted":"90179-06158","name":"Nut (For Rear Wiper Arm Setting)","slug":"nut_for_rear_wiper_arm_setting","description":"","weight":"10","hasReplace":false,"isProduced":true,"manufacturer":"toyota","manufacturerName":"Toyota","isLargeItem":false,"articul":null,"uid":"toyota-9017906158","guid":"B0CFF12D-FF92-4BE3-A676-2CDDE3F8055E","notes":[],"availabilityRate":null},{"id":3705415,"number":"9017908146","numberFormatted":"90179-08146","name":"Nut (For Transmission Control Cable)","slug":"nut_for_transmission_control_cable","description":"","weight":"5","hasReplace":false,"isProduced":true,"manufacturer":"toyota","manufacturerName":"Toyota","isLargeItem":false,"articul":null,"supersessions":[{"type":0,"descriptionValueId":0,"supersessionSet":[{"itemId":5803159,"quantity":1}]}],"uid":"toyota-9017908146","guid":"AB8E4F9A-39CD-41EB-9B2A-41E01250F643","notes":[],"availabilityRate":99},{"id":5803159,"number":"9017908204","numberFormatted":"90179-08204","name":"Nut","slug":"new_genuine_part","description":"","weight":"5","hasReplace":false,"isProduced":true,"manufacturer":"toyota","manufacturerName":"Toyota","isLargeItem":false,"articul":null,"uid":"toyota-9017908204","guid":"2CD90EF4-2BB7-4D49-90BE-4F9555B5124E","notes":[],"availabilityRate":99},{"id":3545283,"number":"9020108135","numberFormatted":"90201-08135","name":"Washer, Plate (For Control Shaft Lower Bracket)","slug":"washer_plate_for_control_shaft_lower_bracket","description":"","weight":"7","hasReplace":false,"isProduced":true,"manufacturer":"toyota","manufacturerName":"Toyota","isLargeItem":false,"articul":null,"uid":"toyota-9020108135","guid":"E0BE8127-1236-11ED-8605-9600009BA0E0","notes":[],"availabilityRate":99},{"id":3788438,"number":"9043043002","numberFormatted":"90430-43002","name":"Gasket, Thermostat","slug":"gasket_thermostat","description":"","weight":"2","hasReplace":false,"isProduced":true,"manufacturer":"toyota","manufacturerName":"Toyota","isLargeItem":false,"articul":null,"uid":"toyota-9043043002","guid":"4F079CBA-EBEC-4241-AC7E-181191F0D57F","notes":[],"availabilityRate":60},{"id":2899984,"number":"9044512065","numberFormatted":"90445-12065","name":"Hose Or Pipe(For Radiator Reserve Tank)","slug":"hose_or_pipe_for_radiator_reserve_tank","description":"","weight":"60","hasReplace":false,"isProduced":true,"manufacturer":"toyota","manufacturerName":"Toyota","isLargeItem":false,"articul":null,"supersessions":[{"type":0,"descriptionValueId":0,"supersessionSet":[{"itemId":2828764,"quantity":1}]}],"uid":"toyota-9044512065","guid":"CB0FA7DE-1236-11ED-8605-9600009BA0E0","notes":[],"availabilityRate":60},{"id":2828764,"number":"9044512078","numberFormatted":"90445-12078","name":"Hose Or Pipe(For Radiator Reserve Tank)","slug":"hose_or_pipe_for_radiator_reserve_tank","description":"","weight":"69","hasReplace":false,"isProduced":true,"manufacturer":"toyota","manufacturerName":"Toyota","isLargeItem":false,"articul":null,"uid":"toyota-9044512078","guid":"E91C4677-6202-4F6B-BEB7-7E17FB17944C","notes":[],"availabilityRate":99},{"id":3848466,"number":"9044512101","numberFormatted":"90445-12101","name":"Hose Or Pipe(For Radiator Reserve Tank)","slug":"hose_or_pipe_for_radiator_reserve_tank","description":"","weight":"70","hasReplace":false,"isProduced":true,"manufacturer":"toyota","manufacturerName":"Toyota","isLargeItem":false,"articul":null,"supersessions":[{"type":0,"descriptionValueId":0,"supersessionSet":[{"itemId":2899984,"quantity":1}]},{"type":0,"descriptionValueId":0,"supersessionSet":[{"itemId":2828764,"quantity":1}]}],"uid":"toyota-9044512101","guid":"EC8EA68B-1236-11ED-8605-9600009BA0E0","notes":[],"availabilityRate":60},{"id":2963776,"number":"9046641008","numberFormatted":"90466-41008","name":"Clamp Or Clip, Hose(For Radiator Inlet)","slug":"clamp_or_clip_hose_for_radiator_inlet","description":"","weight":"40","hasReplace":false,"isProduced":true,"manufacturer":"toyota","manufacturerName":"Toyota","isLargeItem":false,"articul":null,"uid":"toyota-9046641008","guid":"CD1FDB7B-1236-11ED-8605-9600009BA0E0","notes":[],"availabilityRate":99},{"id":5964545,"number":"9046709022","numberFormatted":"90467-09022","name":"Clip","slug":"new_genuine_part","description":"","weight":"3","hasReplace":false,"isProduced":true,"manufacturer":"toyota","manufacturerName":"Toyota","isLargeItem":false,"articul":null,"uid":"toyota-9046709022","guid":"3826E118-1237-11ED-8605-9600009BA0E0","notes":[],"availabilityRate":99},{"id":2816581,"number":"9046711085","numberFormatted":"90467-11085","name":"Clamp Or Clip(For Radiator Reserve Tank Hose)","slug":"clamp_or_clip_for_radiator_reserve_tank_hose","description":"","weight":"1","hasReplace":false,"isProduced":true,"manufacturer":"toyota","manufacturerName":"Toyota","isLargeItem":false,"articul":null,"uid":"toyota-9046711085","guid":"C7DC2005-1236-11ED-8605-9600009BA0E0","notes":[],"availabilityRate":99},{"id":2985092,"number":"9046741002","numberFormatted":"90467-41002","name":"Clamp Or Clip, Hose(For Radiator Inlet)","slug":"clamp_or_clip_hose_for_radiator_inlet","description":"","weight":"31","hasReplace":false,"isProduced":true,"manufacturer":"toyota","manufacturerName":"Toyota","isLargeItem":false,"articul":null,"supersessions":[{"type":0,"descriptionValueId":0,"supersessionSet":[{"itemId":2963776,"quantity":1}]}],"uid":"toyota-9046741002","guid":"CD80A536-1236-11ED-8605-9600009BA0E0","notes":[],"availabilityRate":99},{"id":3572394,"number":"9046742001","numberFormatted":"90467-42001","name":"Clip, Radiator Hose, No.1","slug":"clip_radiator_hose_no_1","description":"","weight":"31","hasReplace":false,"isProduced":true,"manufacturer":"toyota","manufacturerName":"Toyota","isLargeItem":false,"articul":null,"supersessions":[{"type":0,"descriptionValueId":0,"supersessionSet":[{"itemId":2985092,"quantity":1}]},{"type":0,"descriptionValueId":0,"supersessionSet":[{"itemId":2963776,"quantity":1}]}],"uid":"toyota-9046742001","guid":"E2B80540-1236-11ED-8605-9600009BA0E0","notes":[],"availabilityRate":99},{"id":3848488,"number":"9056109005","numberFormatted":"90561-09005","name":"Spacer, Radiator Mounting Insulator","slug":"spacer_radiator_mounting_insulator","description":"","weight":"21","hasReplace":false,"isProduced":true,"manufacturer":"toyota","manufacturerName":"Toyota","isLargeItem":false,"articul":null,"uid":"toyota-9056109005","guid":"EC8EAF0B-1236-11ED-8605-9600009BA0E0","notes":[],"availabilityRate":60},{"id":3788493,"number":"9091601163","numberFormatted":"90916-01163","name":"Hose, Radiator, Outlet","slug":"hose_radiator_outlet","description":"","weight":"120","hasReplace":false,"isProduced":true,"manufacturer":"toyota","manufacturerName":"Toyota","isLargeItem":false,"articul":null,"uid":"toyota-9091601163","guid":"E9DDBEF5-1236-11ED-8605-9600009BA0E0","notes":[],"availabilityRate":60},{"id":3848474,"number":"9091601172","numberFormatted":"90916-01172","name":"Hose, Radiator, Inlet","slug":"hose_radiator_inlet","description":"","weight":"210","hasReplace":false,"isProduced":true,"manufacturer":"toyota","manufacturerName":"Toyota","isLargeItem":false,"articul":null,"uid":"toyota-9091601172","guid":"EC8EA97F-1236-11ED-8605-9600009BA0E0","notes":[],"availabilityRate":60},{"id":3788430,"number":"9091603052","numberFormatted":"90916-03052","name":"Thermostat","slug":"thermostat","description":"","weight":"230","hasReplace":false,"isProduced":true,"manufacturer":"toyota","manufacturerName":"Toyota","isLargeItem":false,"articul":null,"uid":"toyota-9091603052","guid":"F3EC1A4C-E03D-4E43-B010-99778E3FDAD1","notes":[],"availabilityRate":60},{"id":3788431,"number":"9091603071","numberFormatted":"90916-03071","name":"Thermostat","slug":"thermostat","description":"","weight":"220","hasReplace":false,"isProduced":true,"manufacturer":"toyota","manufacturerName":"Toyota","isLargeItem":false,"articul":null,"supersessions":[{"type":0,"descriptionValueId":0,"supersessionSet":[{"itemId":3788430,"quantity":1}]}],"uid":"toyota-9091603071","guid":"E9DD73A7-1236-11ED-8605-9600009BA0E0","notes":[],"availabilityRate":60},{"id":5670922,"number":"9161160845","numberFormatted":"91611-60845","name":"Bolt, Flange","slug":"new_genuine_part","description":"","weight":"19","hasReplace":false,"isProduced":true,"manufacturer":"toyota","manufacturerName":"Toyota","isLargeItem":false,"articul":null,"supersessions":[{"type":0,"descriptionValueId":0,"supersessionSet":[{"itemId":5806330,"quantity":1}]}],"uid":"toyota-9161160845","guid":"2D8E3A43-1237-11ED-8605-9600009BA0E0","notes":[],"availabilityRate":99},{"id":2924613,"number":"9161161020","numberFormatted":"91611-61020","name":"Bolt(For Transaxle & Engine Setting)","slug":"bolt_for_transaxle_engine_setting","description":"","weight":"50","hasReplace":false,"isProduced":true,"manufacturer":"toyota","manufacturerName":"Toyota","isLargeItem":false,"articul":null,"supersessions":[{"type":0,"descriptionValueId":0,"supersessionSet":[{"itemId":3800220,"quantity":1}]}],"uid":"toyota-9161161020","guid":"CB75D724-1236-11ED-8605-9600009BA0E0","notes":[],"availabilityRate":99},{"id":2835914,"number":"9161161025","numberFormatted":"91611-61025","name":"Bolt (For Control Shaft Cover)","slug":"bolt_for_control_shaft_cover","description":"","weight":"20","hasReplace":false,"isProduced":true,"manufacturer":"toyota","manufacturerName":"Toyota","isLargeItem":false,"articul":null,"supersessions":[{"type":0,"descriptionValueId":0,"supersessionSet":[{"itemId":2835915,"quantity":1}]}],"uid":"toyota-9161161025","guid":"C95009B5-1236-11ED-8605-9600009BA0E0","notes":[],"availabilityRate":99},{"id":5806330,"number":"91611B0845","numberFormatted":"91611-B0845","name":"Bolt","slug":"new_genuine_part","description":"","weight":"20","hasReplace":false,"isProduced":true,"manufacturer":"toyota","manufacturerName":"Toyota","isLargeItem":false,"articul":null,"uid":"toyota-91611B0845","guid":"31EDB665-1237-11ED-8605-9600009BA0E0","notes":[],"availabilityRate":null},{"id":2835915,"number":"9161261025","numberFormatted":"91612-61025","name":"Bolt (For Control Shaft Cover)","slug":"bolt_for_control_shaft_cover","description":"","weight":"20","hasReplace":false,"isProduced":true,"manufacturer":"toyota","manufacturerName":"Toyota","isLargeItem":false,"articul":null,"uid":"toyota-9161261025","guid":"C9500A77-1236-11ED-8605-9600009BA0E0","notes":[],"availabilityRate":99},{"id":3800220,"number":"91612B1020","numberFormatted":"91612-B1020","name":"Bolt (For Transfer Case)Cover No.2","slug":"bolt_for_transfer_case_cover_no_2","description":"","weight":"20","hasReplace":false,"isProduced":true,"manufacturer":"toyota","manufacturerName":"Toyota","isLargeItem":false,"articul":null,"uid":"toyota-91612B1020","guid":"17E26056-6EC1-4CCB-8BDD-F3BC73CCC009","notes":[],"availabilityRate":99},{"id":5806477,"number":"9165140614","numberFormatted":"91651-40614","name":"Bolt","slug":"new_genuine_part","description":"","weight":"6","hasReplace":false,"isProduced":true,"manufacturer":"toyota","manufacturerName":"Toyota","isLargeItem":false,"articul":null,"uid":"toyota-9165140614","guid":"72DB139C-C5AB-49CE-9A15-7CF5409C2A05","notes":[],"availabilityRate":99},{"id":5806485,"number":"9165140816","numberFormatted":"91651-40816","name":"Bolt","slug":"new_genuine_part","description":"","weight":"20","hasReplace":false,"isProduced":true,"manufacturer":"toyota","manufacturerName":"Toyota","isLargeItem":false,"articul":null,"uid":"toyota-9165140816","guid":"31EE26DC-1237-11ED-8605-9600009BA0E0","notes":[],"availabilityRate":99},{"id":3120336,"number":"9165160614","numberFormatted":"91651-60614","name":"Bolt (For Rear Differential Breather Plug Oil Deflector)","slug":"bolt_for_rear_differential_breather_plug_oil_deflector","description":"","weight":"10","hasReplace":false,"isProduced":true,"manufacturer":"toyota","manufacturerName":"Toyota","isLargeItem":false,"articul":null,"uid":"toyota-9165160614","guid":"C4D8C5E1-B99A-400A-910D-9525C3BF20A1","notes":[],"availabilityRate":99},{"id":5806495,"number":"9165160620","numberFormatted":"91651-60620","name":"Bolt","slug":"new_genuine_part","description":"","weight":"11","hasReplace":false,"isProduced":true,"manufacturer":"toyota","manufacturerName":"Toyota","isLargeItem":false,"articul":null,"uid":"toyota-9165160620","guid":"31EE2EE1-1237-11ED-8605-9600009BA0E0","notes":[],"availabilityRate":99},{"id":3794259,"number":"9165160830","numberFormatted":"91651-60830","name":"Bolt (For Transfer Power Take-Off Cover)","slug":"bolt_for_transfer_power_take_off_cover","description":"","weight":"20","hasReplace":false,"isProduced":true,"manufacturer":"toyota","manufacturerName":"Toyota","isLargeItem":false,"articul":null,"uid":"toyota-9165160830","guid":"E9F0F02F-1236-11ED-8605-9600009BA0E0","notes":[],"availabilityRate":99},{"id":5806505,"number":"9165160840","numberFormatted":"91651-60840","name":"Bolt","slug":"new_genuine_part","description":"","weight":"20","hasReplace":false,"isProduced":true,"manufacturer":"toyota","manufacturerName":"Toyota","isLargeItem":false,"articul":null,"uid":"toyota-9165160840","guid":"31EE33CB-1237-11ED-8605-9600009BA0E0","notes":[],"availabilityRate":99},{"id":3862781,"number":"9453100800","numberFormatted":"94531-00800","name":"Washer (For Transfer Shift Outer Lever)","slug":"washer_for_transfer_shift_outer_lever","description":"","weight":"5","hasReplace":false,"isProduced":true,"manufacturer":"toyota","manufacturerName":"Toyota","isLargeItem":false,"articul":null,"uid":"toyota-9453100800","guid":"ED4CAF44-1236-11ED-8605-9600009BA0E0","notes":[],"availabilityRate":99},{"id":3753175,"number":"9611110510","numberFormatted":"96111-10510","name":"Clamp Or Clip, Hose(For Radiator Outlet No.1)","slug":"clamp_or_clip_hose_for_radiator_outlet_no_1","description":"","weight":"28","hasReplace":false,"isProduced":true,"manufacturer":"toyota","manufacturerName":"Toyota","isLargeItem":false,"articul":null,"uid":"toyota-9611110510","guid":"E95B0DDC-1236-11ED-8605-9600009BA0E0","notes":[],"availabilityRate":99},{"id":2835170,"number":"9611110580","numberFormatted":"96111-10580","name":"Clamp(For Air Cleaner Hose, No.1)","slug":"clamp_for_air_cleaner_hose_no_1","description":"","weight":"30","hasReplace":false,"isProduced":true,"manufacturer":"toyota","manufacturerName":"Toyota","isLargeItem":false,"articul":null,"uid":"toyota-9611110580","guid":"C94DF14E-1236-11ED-8605-9600009BA0E0","notes":[],"availabilityRate":99},{"id":3625581,"number":"9611210330","numberFormatted":"96112-10330","name":"Clamp Or Clip, No.1(For Air Injection System Hose, No.1)","slug":"clamp_or_clip_no_1_for_air_injection_system_hose_no_1","description":"","weight":"20","hasReplace":false,"isProduced":true,"manufacturer":"toyota","manufacturerName":"Toyota","isLargeItem":false,"articul":null,"uid":"toyota-9611210330","guid":"E44655DC-1236-11ED-8605-9600009BA0E0","notes":[],"availabilityRate":99},{"id":3848479,"number":"9955470185","numberFormatted":"99554-70185","name":"Hose, Radiator, Outlet","slug":"hose_radiator_outlet","description":"","weight":"170","hasReplace":false,"isProduced":true,"manufacturer":"toyota","manufacturerName":"Toyota","isLargeItem":false,"articul":null,"uid":"toyota-9955470185","guid":"EC8EAB52-1236-11ED-8605-9600009BA0E0","notes":[],"availabilityRate":60}],"model":{"id":7068,"path":"land_cruiser","name":"Land Cruiser","techType":"car","manufacturer":{"slug":"toyota","name":"Toyota"},"childrenCount":0,"oneChildPath":"","generationCount":0,"oneGenerationKey":"","notes":[]},"generation":{"techType":"car","manufacturer":{"slug":"toyota","name":"Toyota"},"modelPath":"land_cruiser","key":"land_cruiser-gen_7","image":"land_cruiser\/gen_7","name":"7th Gen","yearRange":"1980 \u2014 1992","variantIds":[],"variantCount":0,"oneVariantPath":"land_cruiser\/fj60-fj60lv_ka-us-2f-mtm-4f-usa-wgv"},"paramNames":{"name":"Name","sales_region":"Sales Region","engine":"Engine","atm_mtm":"Atm,Mtm","gear_shift_type":"Gear Shift Type","destination":"Destination","body":"Body","date_range":"Production Dates"},"seoInfo":{"title":"Radiator & Water Outlet","subtitle":"Toyota Land Cruiser \u2022 FJ60","welcomeText":[],"footerHeader":"","footerText":[],"metaTitle":"Toyota Land Cruiser FJ60 Radiator & Water Outlet | YoshiParts","metaDescription":"Shop for Toyota Radiator & Water Outlet used in Toyota Land Cruiser FJ60 and enjoy worldwide shipping from our authorized dealer. Genuine Toyota parts."},"breadcrumbs":[{"label":"Home","url":"https:\/\/yoshiparts.com\/"},{"label":"Toyota Genuine Parts","url":"https:\/\/yoshiparts.com\/parts\/toyota\/tech"},{"label":"Toyota Car Parts","url":"https:\/\/yoshiparts.com\/parts\/car\/toyota"},{"label":"Toyota Land Cruiser","url":"https:\/\/yoshiparts.com\/parts\/car\/toyota\/land_cruiser"},{"label":"7th Gen","url":"https:\/\/yoshiparts.com\/parts\/car\/toyota\/land_cruiser\/params\/land_cruiser-gen_7\/one"},{"label":"FJ60","url":"https:\/\/yoshiparts.com\/parts\/car\/toyota\/diagrams\/land_cruiser\/fj60-fj60lv_ka-us-2f-mtm-4f-usa-wgv"},{"label":"Toyota Land Cruiser FJ60 Radiator & Water Outlet","url":"https:\/\/yoshiparts.com\/parts\/car\/toyota\/products\/land_cruiser\/fj60-fj60lv_ka-us-2f-mtm-4f-usa-wgv\/1726002_15"}],"jsonld":[{"@context":"http:\/\/schema.org","@type":"BreadcrumbList","itemListElement":[{"@type":"ListItem","position":1,"item":{"@id":"https:\/\/yoshiparts.com\/","name":"Home"}},{"@type":"ListItem","position":2,"item":{"@id":"https:\/\/yoshiparts.com\/parts\/toyota\/tech","name":"Toyota Genuine Parts"}},{"@type":"ListItem","position":3,"item":{"@id":"https:\/\/yoshiparts.com\/parts\/car\/toyota","name":"Toyota Car Parts"}},{"@type":"ListItem","position":4,"item":{"@id":"https:\/\/yoshiparts.com\/parts\/car\/toyota\/land_cruiser","name":"Toyota Land Cruiser"}},{"@type":"ListItem","position":5,"item":{"@id":"https:\/\/yoshiparts.com\/parts\/car\/toyota\/land_cruiser\/params\/land_cruiser-gen_7\/one","name":"7th Gen"}},{"@type":"ListItem","position":6,"item":{"@id":"https:\/\/yoshiparts.com\/parts\/car\/toyota\/diagrams\/land_cruiser\/fj60-fj60lv_ka-us-2f-mtm-4f-usa-wgv","name":"FJ60"}},{"@type":"ListItem","position":7,"item":{"@id":"https:\/\/yoshiparts.com\/parts\/car\/toyota\/products\/land_cruiser\/fj60-fj60lv_ka-us-2f-mtm-4f-usa-wgv\/1726002_15","name":"Toyota Land Cruiser FJ60 Radiator & Water Outlet"}}]}]}