{"manufacturer":"toyota","diagram":{"id":1288070,"globalId":1750325,"slug":"seat_belt","name":"Seat Belt","chapterName":null,"chapterId":null,"position":118,"section":null,"sectionName":null,"hotspots":{"73150":[[201,942,251,957]],"73210":[[142,314,191,329],[38,818,88,833]],"73210B":[[282,186,342,201],[456,277,516,292],[263,705,323,719],[470,717,530,732]],"73220":[[540,421,589,436],[566,851,615,866]],"73230":[[278,548,328,564],[390,658,439,673],[132,915,181,929]],"73240":[[146,556,195,571],[326,582,376,597],[560,681,611,695],[164,1005,214,1020],[339,1010,389,1025]],"73330":[[345,81,394,96]],"73340":[[574,188,623,202]],"73350":[[423,237,472,252]],"9010511056":[[551,632,660,645]],"9020411025":[[551,654,659,668]],"9354014012":[[532,480,621,494],[571,922,659,935]]},"description":" (8008- )","additionalInfo":null,"dateRange":" [08.1980-]","uid":"1750325_118","image":{"originals":"https:\/\/epc.partsbooster.com\/schemas\/toyota\/fd16236d5f0ea3aa4025f0588f69ae3b.png","thumbnails":"https:\/\/epc.partsbooster.com\/schemas\/toyota\/fd16236d5f0ea3aa4025f0588f69ae3b.png"},"imageScaleRatio":1},"diagramsInSection":[{"slug":"seat_belt","uid":"1750325_118","image":{"originals":"https:\/\/epc.partsbooster.com\/schemas\/toyota\/fd16236d5f0ea3aa4025f0588f69ae3b.png","thumbnails":"https:\/\/epc.partsbooster.com\/schemas\/toyota\/fd16236d5f0ea3aa4025f0588f69ae3b.png"},"image_scale_ratio":1}],"variant":{"id":39958,"path":"land_cruiser\/fj60-fj60lv_ka-us-2f-mtm-4f-usa-wgv","parentPath":"land_cruiser","techType":"car","manufacturer":{"slug":"toyota","name":"Toyota"},"generationKey":"land_cruiser-gen_7","header":"Toyota Land Cruiser","subheader":"FJ60","params":[["sales_region",["USA","US"]],["engine",["2F","4200CC"]],["atm_mtm",["MTM","MANUAL TRANSMISSION"]],["gear_shift_type",["4F","MTM, 4-SPEED FLOOR SHIFT"]],["destination",["USA","UNITED STATES OF AMERICA"]],["body",["WGV","STATION WAGON"]],["date_range",["Sep 1986 \u2013 Aug 1987",""]]],"options":[],"vinParams":[]},"countInSection":1,"diagramItems":[{"id":41438766,"refNumber":"73210","qt":1,"itemId":3854738,"description":[["Year",["08.1986-08.1987"]],["Note",["FJ60,HJ60","GRAY,GRAY"]]],"dateRange":"","isSearched":false},{"id":41438767,"refNumber":"73210","qt":1,"itemId":3854739,"description":[["Year",["08.1986-08.1987"]],["Note",["FJ60,HJ60","BROWN,SEPIA BROWN"]]],"dateRange":"","isSearched":false},{"id":41438768,"refNumber":"73220","qt":1,"itemId":3854762,"description":[["Year",["08.1986-08.1987"]],["Note",["FJ60,HJ60","GRAY,GRAY"]]],"dateRange":"","isSearched":false},{"id":41438769,"refNumber":"73220","qt":1,"itemId":3854763,"description":[["Year",["08.1986-08.1987"]],["Note",["FJ60,HJ60","BROWN,SEPIA BROWN"]]],"dateRange":"","isSearched":false},{"id":41438770,"refNumber":"73230","qt":1,"itemId":3854788,"description":[["Year",["04.1985-08.1987"]],["Note",["BJ60,FJ60,HJ60","GRAY,GRAY"]]],"dateRange":"","isSearched":false},{"id":41438771,"refNumber":"73230","qt":1,"itemId":3854798,"description":[["Year",["04.1985-08.1987"]],["Note",["BJ60,FJ60,HJ60","BROWN,SEPIA BROWN"]]],"dateRange":"","isSearched":false},{"id":41438772,"refNumber":"73240","qt":1,"itemId":3854829,"description":[["Year",["04.1986-08.1987"]],["Note",["FJ60","GRAY,SHADOW GRAY"]]],"dateRange":"","isSearched":false},{"id":41438773,"refNumber":"73240","qt":1,"itemId":3854830,"description":[["Year",["04.1986-08.1987"]],["Note",["FJ60","BROWN,SEPIA BROWN"]]],"dateRange":"","isSearched":false},{"id":41438774,"refNumber":"9010511056","qt":1,"itemId":5801776,"description":[],"dateRange":"","isSearched":false},{"id":41438775,"refNumber":"9020411025","qt":1,"itemId":5803404,"description":[],"dateRange":"","isSearched":false},{"id":41438776,"refNumber":"9354014012","qt":1,"itemId":5974740,"description":[],"dateRange":"","isSearched":false}],"sectionRefs":null,"products":[{"id":3854738,"number":"7321090A2603","numberFormatted":"73210-90A26-03","name":"Belt Assy, Front Seat Outer, Rh","slug":"belt_assy_front_seat_outer_rh","description":"","weight":"1120","hasReplace":false,"isProduced":true,"manufacturer":"toyota","manufacturerName":"Toyota","isLargeItem":false,"articul":null,"supersessions":[{"type":0,"descriptionValueId":0,"supersessionSet":[{"itemId":4478113,"quantity":1}]}],"uid":"toyota-7321090A2603","guid":"ED21F951-1236-11ED-8605-9600009BA0E0","notes":[],"availabilityRate":60},{"id":3854739,"number":"7321090A2606","numberFormatted":"73210-90A26-06","name":"Belt Assy, Front Seat Outer, Rh","slug":"belt_assy_front_seat_outer_rh","description":"","weight":"1120","hasReplace":false,"isProduced":true,"manufacturer":"toyota","manufacturerName":"Toyota","isLargeItem":false,"articul":null,"supersessions":[{"type":0,"descriptionValueId":0,"supersessionSet":[{"itemId":4478114,"quantity":1}]},{"type":0,"descriptionValueId":0,"supersessionSet":[{"itemId":4478113,"quantity":1}]}],"uid":"toyota-7321090A2606","guid":"ED21FA03-1236-11ED-8605-9600009BA0E0","notes":[],"availabilityRate":60},{"id":4478113,"number":"7321090A2903","numberFormatted":"73210-90A29-03","name":"Belt Assy, Front Seat Outer, Rh","slug":"belt_assy_front_seat_outer_rh","description":"","weight":"1120","hasReplace":false,"isProduced":true,"manufacturer":"toyota","manufacturerName":"Toyota","isLargeItem":false,"articul":null,"uid":"toyota-7321090A2903","guid":"041C79A5-1237-11ED-8605-9600009BA0E0","notes":[],"availabilityRate":60},{"id":4478114,"number":"7321090A2906","numberFormatted":"73210-90A29-06","name":"Belt Assy, Front Seat Outer, Rh","slug":"belt_assy_front_seat_outer_rh","description":"","weight":"1120","hasReplace":false,"isProduced":true,"manufacturer":"toyota","manufacturerName":"Toyota","isLargeItem":false,"articul":null,"supersessions":[{"type":0,"descriptionValueId":0,"supersessionSet":[{"itemId":4478113,"quantity":1}]}],"uid":"toyota-7321090A2906","guid":"041C7A77-1237-11ED-8605-9600009BA0E0","notes":[],"availabilityRate":60},{"id":3854762,"number":"7322090A1503","numberFormatted":"73220-90A15-03","name":"Belt Assy, Front Seat Outer, Lh","slug":"belt_assy_front_seat_outer_lh","description":"","weight":"1140","hasReplace":false,"isProduced":true,"manufacturer":"toyota","manufacturerName":"Toyota","isLargeItem":false,"articul":null,"supersessions":[{"type":0,"descriptionValueId":0,"supersessionSet":[{"itemId":4478117,"quantity":1}]}],"uid":"toyota-7322090A1503","guid":"ED22230F-1236-11ED-8605-9600009BA0E0","notes":[],"availabilityRate":60},{"id":3854763,"number":"7322090A1506","numberFormatted":"73220-90A15-06","name":"Belt Assy, Front Seat Outer, Lh","slug":"belt_assy_front_seat_outer_lh","description":"","weight":"1120","hasReplace":false,"isProduced":true,"manufacturer":"toyota","manufacturerName":"Toyota","isLargeItem":false,"articul":null,"supersessions":[{"type":0,"descriptionValueId":0,"supersessionSet":[{"itemId":4478118,"quantity":1}]},{"type":0,"descriptionValueId":0,"supersessionSet":[{"itemId":4478117,"quantity":1}]}],"uid":"toyota-7322090A1506","guid":"ED2225AE-1236-11ED-8605-9600009BA0E0","notes":[],"availabilityRate":60},{"id":4478117,"number":"7322090A1703","numberFormatted":"73220-90A17-03","name":"Belt Assy, Front Seat Outer, Lh","slug":"belt_assy_front_seat_outer_lh","description":"","weight":"1140","hasReplace":false,"isProduced":true,"manufacturer":"toyota","manufacturerName":"Toyota","isLargeItem":false,"articul":null,"uid":"toyota-7322090A1703","guid":"041C7CF4-1237-11ED-8605-9600009BA0E0","notes":[],"availabilityRate":60},{"id":4478118,"number":"7322090A1706","numberFormatted":"73220-90A17-06","name":"Belt Assy, Front Seat Outer, Lh","slug":"belt_assy_front_seat_outer_lh","description":"","weight":"1100","hasReplace":false,"isProduced":true,"manufacturer":"toyota","manufacturerName":"Toyota","isLargeItem":false,"articul":null,"supersessions":[{"type":0,"descriptionValueId":0,"supersessionSet":[{"itemId":4478117,"quantity":1}]}],"uid":"toyota-7322090A1706","guid":"041C7DC4-1237-11ED-8605-9600009BA0E0","notes":[],"availabilityRate":60},{"id":3854788,"number":"7323090A1703","numberFormatted":"73230-90A17-03","name":"Belt Assy, Front Seat Inner, Rh","slug":"belt_assy_front_seat_inner_rh","description":"","weight":"400","hasReplace":false,"isProduced":true,"manufacturer":"toyota","manufacturerName":"Toyota","isLargeItem":false,"articul":null,"supersessions":[{"type":0,"descriptionValueId":0,"supersessionSet":[{"itemId":3854799,"quantity":1}]}],"uid":"toyota-7323090A1703","guid":"ED223776-1236-11ED-8605-9600009BA0E0","notes":[],"availabilityRate":60},{"id":3854798,"number":"7323090A1706","numberFormatted":"73230-90A17-06","name":"Belt Assy, Front Seat Inner, Rh","slug":"belt_assy_front_seat_inner_rh","description":"","weight":"400","hasReplace":false,"isProduced":true,"manufacturer":"toyota","manufacturerName":"Toyota","isLargeItem":false,"articul":null,"supersessions":[{"type":0,"descriptionValueId":0,"supersessionSet":[{"itemId":3854799,"quantity":1}]}],"uid":"toyota-7323090A1706","guid":"ED223B40-1236-11ED-8605-9600009BA0E0","notes":[],"availabilityRate":60},{"id":3854799,"number":"7323090A1713","numberFormatted":"73230-90A17-13","name":"Belt Assy, Front Seat Inner, Rh","slug":"belt_assy_front_seat_inner_rh","description":"","weight":"410","hasReplace":false,"isProduced":true,"manufacturer":"toyota","manufacturerName":"Toyota","isLargeItem":false,"articul":null,"uid":"toyota-7323090A1713","guid":"ED223C33-1236-11ED-8605-9600009BA0E0","notes":[],"availabilityRate":60},{"id":3854829,"number":"7324090A2003","numberFormatted":"73240-90A20-03","name":"Belt Assy, Front Seat Inner, Lh","slug":"belt_assy_front_seat_inner_lh","description":"","weight":"410","hasReplace":false,"isProduced":true,"manufacturer":"toyota","manufacturerName":"Toyota","isLargeItem":false,"articul":null,"uid":"toyota-7324090A2003","guid":"ED224889-1236-11ED-8605-9600009BA0E0","notes":[],"availabilityRate":60},{"id":3854830,"number":"7324090A2006","numberFormatted":"73240-90A20-06","name":"Belt Assy, Front Seat Inner, Lh","slug":"belt_assy_front_seat_inner_lh","description":"","weight":"420","hasReplace":false,"isProduced":true,"manufacturer":"toyota","manufacturerName":"Toyota","isLargeItem":false,"articul":null,"supersessions":[{"type":0,"descriptionValueId":0,"supersessionSet":[{"itemId":3854829,"quantity":1}]}],"uid":"toyota-7324090A2006","guid":"ED2248D3-1236-11ED-8605-9600009BA0E0","notes":[],"availabilityRate":60},{"id":5801776,"number":"9010511056","numberFormatted":"90105-11056","name":"Bolt","slug":"new_genuine_part","description":"","weight":"30","hasReplace":false,"isProduced":true,"manufacturer":"toyota","manufacturerName":"Toyota","isLargeItem":false,"articul":null,"uid":"toyota-9010511056","guid":"31DF9107-1237-11ED-8605-9600009BA0E0","notes":[],"availabilityRate":60},{"id":5803404,"number":"9020411025","numberFormatted":"90204-11025","name":"New Genuine Part","slug":"new_genuine_part","description":"","weight":"4","hasReplace":false,"isProduced":true,"manufacturer":"toyota","manufacturerName":"Toyota","isLargeItem":false,"articul":null,"uid":"toyota-9020411025","guid":"31E47B8D-1237-11ED-8605-9600009BA0E0","notes":[],"availabilityRate":60},{"id":5974740,"number":"9354014012","numberFormatted":"93540-14012","name":"Screw","slug":"new_genuine_part","description":"","weight":"3","hasReplace":false,"isProduced":true,"manufacturer":"toyota","manufacturerName":"Toyota","isLargeItem":false,"articul":null,"uid":"toyota-9354014012","guid":"3848550D-1237-11ED-8605-9600009BA0E0","notes":[],"availabilityRate":99}],"model":{"id":7068,"path":"land_cruiser","name":"Land Cruiser","techType":"car","manufacturer":{"slug":"toyota","name":"Toyota"},"childrenCount":0,"oneChildPath":"","generationCount":0,"oneGenerationKey":"","notes":[]},"generation":{"techType":"car","manufacturer":{"slug":"toyota","name":"Toyota"},"modelPath":"land_cruiser","key":"land_cruiser-gen_7","image":"land_cruiser\/gen_7","name":"7th Gen","yearRange":"1980 \u2014 1992","variantIds":[],"variantCount":0,"oneVariantPath":"land_cruiser\/fj60-fj60lv_ka-us-2f-mtm-4f-usa-wgv"},"paramNames":{"name":"Name","sales_region":"Sales Region","engine":"Engine","atm_mtm":"Atm,Mtm","gear_shift_type":"Gear Shift Type","destination":"Destination","body":"Body","date_range":"Production Dates"},"seoInfo":{"title":"Seat Belt","subtitle":"Toyota Land Cruiser \u2022 FJ60","welcomeText":[],"footerHeader":"","footerText":[],"metaTitle":"Toyota Land Cruiser FJ60 Seat Belt | YoshiParts","metaDescription":"Shop for Toyota Seat Belt used in Toyota Land Cruiser FJ60 and enjoy worldwide shipping from our authorized dealer. Genuine Toyota parts."},"breadcrumbs":[{"label":"Home","url":"https:\/\/yoshiparts.com\/"},{"label":"Toyota Genuine Parts","url":"https:\/\/yoshiparts.com\/parts\/toyota\/tech"},{"label":"Toyota Car Parts","url":"https:\/\/yoshiparts.com\/parts\/car\/toyota"},{"label":"Toyota Land Cruiser","url":"https:\/\/yoshiparts.com\/parts\/car\/toyota\/land_cruiser"},{"label":"7th Gen","url":"https:\/\/yoshiparts.com\/parts\/car\/toyota\/land_cruiser\/params\/land_cruiser-gen_7\/one"},{"label":"FJ60","url":"https:\/\/yoshiparts.com\/parts\/car\/toyota\/diagrams\/land_cruiser\/fj60-fj60lv_ka-us-2f-mtm-4f-usa-wgv"},{"label":"Toyota Land Cruiser FJ60 Seat Belt","url":"https:\/\/yoshiparts.com\/parts\/car\/toyota\/products\/land_cruiser\/fj60-fj60lv_ka-us-2f-mtm-4f-usa-wgv\/1750325_118"}],"jsonld":[{"@context":"http:\/\/schema.org","@type":"BreadcrumbList","itemListElement":[{"@type":"ListItem","position":1,"item":{"@id":"https:\/\/yoshiparts.com\/","name":"Home"}},{"@type":"ListItem","position":2,"item":{"@id":"https:\/\/yoshiparts.com\/parts\/toyota\/tech","name":"Toyota Genuine Parts"}},{"@type":"ListItem","position":3,"item":{"@id":"https:\/\/yoshiparts.com\/parts\/car\/toyota","name":"Toyota Car Parts"}},{"@type":"ListItem","position":4,"item":{"@id":"https:\/\/yoshiparts.com\/parts\/car\/toyota\/land_cruiser","name":"Toyota Land Cruiser"}},{"@type":"ListItem","position":5,"item":{"@id":"https:\/\/yoshiparts.com\/parts\/car\/toyota\/land_cruiser\/params\/land_cruiser-gen_7\/one","name":"7th Gen"}},{"@type":"ListItem","position":6,"item":{"@id":"https:\/\/yoshiparts.com\/parts\/car\/toyota\/diagrams\/land_cruiser\/fj60-fj60lv_ka-us-2f-mtm-4f-usa-wgv","name":"FJ60"}},{"@type":"ListItem","position":7,"item":{"@id":"https:\/\/yoshiparts.com\/parts\/car\/toyota\/products\/land_cruiser\/fj60-fj60lv_ka-us-2f-mtm-4f-usa-wgv\/1750325_118","name":"Toyota Land Cruiser FJ60 Seat Belt"}}]}]}