[{"cost":1.87,"packQuantity":1,"productUid":"toyota-9011908718","shipperId":3,"currencyCode":"USD","maxQuantity":null,"handlingDaysFrom":5,"handlingDaysTo":10,"originalCost":null,"originalCurrencyCode":"USD"},{"cost":0.96,"packQuantity":1,"productUid":"toyota-9017906158","shipperId":3,"currencyCode":"USD","maxQuantity":null,"handlingDaysFrom":5,"handlingDaysTo":10,"originalCost":null,"originalCurrencyCode":"USD"},{"cost":8,"packQuantity":1,"productUid":"toyota-8212490A01","shipperId":2,"currencyCode":"USD","maxQuantity":null,"handlingDaysFrom":5,"handlingDaysTo":7,"originalCost":null,"originalCurrencyCode":"USD"},{"cost":29.97,"packQuantity":1,"productUid":"toyota-8212590A06","shipperId":2,"currencyCode":"USD","maxQuantity":null,"handlingDaysFrom":5,"handlingDaysTo":7,"originalCost":null,"originalCurrencyCode":"USD"},{"cost":1266.95,"packQuantity":1,"productUid":"toyota-8213190A99","shipperId":2,"currencyCode":"USD","maxQuantity":null,"handlingDaysFrom":5,"handlingDaysTo":7,"originalCost":null,"originalCurrencyCode":"USD"},{"cost":53.07,"packQuantity":1,"productUid":"toyota-8213290A08","shipperId":2,"currencyCode":"USD","maxQuantity":null,"handlingDaysFrom":5,"handlingDaysTo":7,"originalCost":null,"originalCurrencyCode":"USD"},{"cost":32.21,"packQuantity":1,"productUid":"toyota-8214190A01","shipperId":2,"currencyCode":"USD","maxQuantity":null,"handlingDaysFrom":5,"handlingDaysTo":7,"originalCost":null,"originalCurrencyCode":"USD"},{"cost":12.17,"packQuantity":1,"productUid":"toyota-8234512050","shipperId":2,"currencyCode":"USD","maxQuantity":null,"handlingDaysFrom":5,"handlingDaysTo":7,"originalCost":null,"originalCurrencyCode":"USD"},{"cost":1.17,"packQuantity":1,"productUid":"toyota-9011906005","shipperId":2,"currencyCode":"USD","maxQuantity":null,"handlingDaysFrom":5,"handlingDaysTo":7,"originalCost":null,"originalCurrencyCode":"USD"},{"cost":2.67,"packQuantity":1,"productUid":"toyota-9011908116","shipperId":2,"currencyCode":"USD","maxQuantity":null,"handlingDaysFrom":5,"handlingDaysTo":7,"originalCost":null,"originalCurrencyCode":"USD"},{"cost":2.17,"packQuantity":1,"productUid":"toyota-9011908157","shipperId":2,"currencyCode":"USD","maxQuantity":null,"handlingDaysFrom":5,"handlingDaysTo":7,"originalCost":null,"originalCurrencyCode":"USD"},{"cost":2.67,"packQuantity":1,"productUid":"toyota-9011908718","shipperId":2,"currencyCode":"USD","maxQuantity":null,"handlingDaysFrom":5,"handlingDaysTo":7,"originalCost":null,"originalCurrencyCode":"USD"},{"cost":2,"packQuantity":1,"productUid":"toyota-9017905003","shipperId":2,"currencyCode":"USD","maxQuantity":null,"handlingDaysFrom":5,"handlingDaysTo":7,"originalCost":null,"originalCurrencyCode":"USD"},{"cost":1,"packQuantity":1,"productUid":"toyota-9017906158","shipperId":2,"currencyCode":"USD","maxQuantity":null,"handlingDaysFrom":5,"handlingDaysTo":7,"originalCost":null,"originalCurrencyCode":"USD"},{"cost":14,"packQuantity":1,"productUid":"toyota-9098007003","shipperId":2,"currencyCode":"USD","maxQuantity":null,"handlingDaysFrom":5,"handlingDaysTo":7,"originalCost":null,"originalCurrencyCode":"USD"},{"cost":15,"packQuantity":1,"productUid":"toyota-9098007048","shipperId":2,"currencyCode":"USD","maxQuantity":null,"handlingDaysFrom":5,"handlingDaysTo":7,"originalCost":null,"originalCurrencyCode":"USD"},{"cost":15.5,"packQuantity":1,"productUid":"toyota-9098007251","shipperId":2,"currencyCode":"USD","maxQuantity":null,"handlingDaysFrom":5,"handlingDaysTo":7,"originalCost":null,"originalCurrencyCode":"USD"},{"cost":25.07,"packQuantity":1,"productUid":"toyota-9098208135","shipperId":2,"currencyCode":"USD","maxQuantity":null,"handlingDaysFrom":5,"handlingDaysTo":7,"originalCost":null,"originalCurrencyCode":"USD"}]