{"product":{"id":6860042371258,"title":"Rear Body to Hatch Weatherstrip \/ Seal FJ60,FJ62,HJ,BJ - 1981-1990","body_html":"\u003cp\u003eReproduction 60 Series Landcruiser Weatherstrip\u003c\/p\u003e\n\u003cp\u003eThis weatherstrip fits the rear body to hatch area fits 1981 - 1990\u003c\/p\u003e","vendor":"Cruiser Corps","product_type":"Weatherstrip","created_at":"2021-09-15T17:02:10-05:00","handle":"60-series-rear-hatch-body-weatherstrip","updated_at":"2023-10-02T18:05:27-05:00","published_at":"2021-09-16T00:15:57-05:00","template_suffix":"","published_scope":"web","tags":"1981, 1982, 1983, 1984, 1985, 1986, 1987, 1988, 1989, 1990, BJ, BJ60, BJ61, eBay, feed-cond-new, FJ60, FJ62, Hatch, HJ60, HJ61, Rubber, Seals, weatherstrip, Weatherstrip and Rubber","variants":[{"id":40458399940794,"product_id":6860042371258,"title":"Default Title","price":"94.95","sku":"522-120","position":1,"compare_at_price":"","fulfillment_service":"manual","inventory_management":"shopify","option1":"Default Title","option2":null,"option3":null,"created_at":"2021-09-15T17:02:10-05:00","updated_at":"2023-10-02T18:05:27-05:00","taxable":true,"barcode":"522-120","grams":907,"image_id":null,"weight":2.0,"weight_unit":"lb","tax_code":"","requires_shipping":true,"quantity_rule":{"min":1,"max":null,"increment":1},"quantity_price_breaks":[]}],"options":[{"id":8807667695802,"product_id":6860042371258,"name":"Title","position":1,"values":["Default Title"]}],"images":[{"id":29533656416442,"product_id":6860042371258,"position":1,"created_at":"2021-09-15T17:05:12-05:00","updated_at":"2021-09-15T17:05:12-05:00","alt":null,"width":5184,"height":3456,"src":"https:\/\/cdn.shopify.com\/s\/files\/1\/0027\/8770\/4898\/products\/IMG_2778.jpg?v=1631743512","variant_ids":[]},{"id":29533658677434,"product_id":6860042371258,"position":2,"created_at":"2021-09-15T17:05:28-05:00","updated_at":"2021-09-15T17:05:28-05:00","alt":null,"width":5184,"height":3456,"src":"https:\/\/cdn.shopify.com\/s\/files\/1\/0027\/8770\/4898\/products\/IMG_2781.jpg?v=1631743528","variant_ids":[]},{"id":29533660643514,"product_id":6860042371258,"position":3,"created_at":"2021-09-15T17:05:42-05:00","updated_at":"2021-09-15T17:05:42-05:00","alt":null,"width":3456,"height":5184,"src":"https:\/\/cdn.shopify.com\/s\/files\/1\/0027\/8770\/4898\/products\/IMG_2779.jpg?v=1631743542","variant_ids":[]}],"image":{"id":29533656416442,"product_id":6860042371258,"position":1,"created_at":"2021-09-15T17:05:12-05:00","updated_at":"2021-09-15T17:05:12-05:00","alt":null,"width":5184,"height":3456,"src":"https:\/\/cdn.shopify.com\/s\/files\/1\/0027\/8770\/4898\/products\/IMG_2778.jpg?v=1631743512","variant_ids":[]}}}