{"product":{"id":1462174580802,"title":"AISIN Cooling Fan Clutch FJ40, FJ45, FJ55, FJ60, FJ62 1976-1990","body_html":"\u003cp\u003eFits 8\/1976 - 1\/1990 - FJ40\/45, FJ55, FJ60\/62\u003c\/p\u003e\n\u003cp\u003e\u003cbr\u003eEngineered to exacting OE specifications, AISIN Fan Clutch quickly adjusts to temperature changes to provide efficient, controlled cooling. Providing optimal cooling performance without sacrificing engine efficiency, AISIN Fan Clutches are always OE Matched.\u003c\/p\u003e","vendor":"Aisin","product_type":"Engine","created_at":"2018-07-20T09:32:59-05:00","handle":"aisin-cooling-fan-clutch","updated_at":"2023-10-02T18:05:29-05:00","published_at":"2018-07-20T09:32:58-05:00","template_suffix":"","published_scope":"web","tags":"1976, 1977, 1978, 1979, 1980, 1981, 1982, 1983, 1984, 1985, 1986, 1987, 1988, 1989, 1990, Cooling \/ Heating, Fan Clutch, feed-cond-new, FJ40, FJ45, FJ55, FJ60, FJ62","variants":[{"id":12736724041794,"product_id":1462174580802,"title":"Default Title","price":"98.51","sku":"545-117","position":1,"compare_at_price":"","fulfillment_service":"manual","inventory_management":"shopify","option1":"Default Title","option2":null,"option3":null,"created_at":"2018-07-20T09:32:59-05:00","updated_at":"2023-10-02T18:05:29-05:00","taxable":true,"barcode":"545-117","grams":2268,"image_id":null,"weight":5.0,"weight_unit":"lb","tax_code":"P0000000","requires_shipping":true,"quantity_rule":{"min":1,"max":null,"increment":1},"quantity_price_breaks":[]}],"options":[{"id":1925087658050,"product_id":1462174580802,"name":"Title","position":1,"values":["Default Title"]}],"images":[{"id":3882475159618,"product_id":1462174580802,"position":1,"created_at":"2018-07-20T09:32:59-05:00","updated_at":"2019-10-21T23:49:06-05:00","alt":"fj60 fan clutch","width":1000,"height":694,"src":"https:\/\/cdn.shopify.com\/s\/files\/1\/0027\/8770\/4898\/products\/1f1c8edf823d28af58429d4d1d3b62f6.jpg?v=1571719746","variant_ids":[]},{"id":3882475192386,"product_id":1462174580802,"position":2,"created_at":"2018-07-20T09:32:59-05:00","updated_at":"2019-10-21T23:49:06-05:00","alt":"fj60 fan clutch","width":1000,"height":691,"src":"https:\/\/cdn.shopify.com\/s\/files\/1\/0027\/8770\/4898\/products\/d64ec567cc01eab6a4f393048ef946d6.jpg?v=1571719746","variant_ids":[]}],"image":{"id":3882475159618,"product_id":1462174580802,"position":1,"created_at":"2018-07-20T09:32:59-05:00","updated_at":"2019-10-21T23:49:06-05:00","alt":"fj60 fan clutch","width":1000,"height":694,"src":"https:\/\/cdn.shopify.com\/s\/files\/1\/0027\/8770\/4898\/products\/1f1c8edf823d28af58429d4d1d3b62f6.jpg?v=1571719746","variant_ids":[]}}}