{"product":{"id":1462571040834,"title":"Rear Left Manual Window Regulator FJ60, FJ62 1980-1990","body_html":"Aftermarket Fits FJ60\/FJ62 8\/80-1\/90 This manual regulator is the perfect cost saving replacement for the original. Fits rear driver side\/left door.","vendor":"Cruiser Corps","product_type":"Interior","created_at":"2018-07-20T14:14:59-05:00","handle":"fj60-manual-window-regulator-rear-left","updated_at":"2023-10-02T18:06:01-05:00","published_at":"2018-07-20T14:14:59-05:00","template_suffix":"","published_scope":"web","tags":"1980, 1981, 1982, 1983, 1984, 1985, 1986, 1987, 1988, 1989, 1990, Door Parts, Door Window Regulator, feed-cond-new, FJ60, FJ62","variants":[{"id":12738343108674,"product_id":1462571040834,"title":"Default Title","price":"42.95","sku":"549-309","position":1,"compare_at_price":"","fulfillment_service":"manual","inventory_management":"shopify","option1":"Default Title","option2":null,"option3":null,"created_at":"2018-07-20T14:15:00-05:00","updated_at":"2023-10-02T18:06:01-05:00","taxable":true,"barcode":"549-309","grams":1361,"image_id":null,"weight":3.0,"weight_unit":"lb","tax_code":"","requires_shipping":true,"quantity_rule":{"min":1,"max":null,"increment":1},"quantity_price_breaks":[]}],"options":[{"id":1925559877698,"product_id":1462571040834,"name":"Title","position":1,"values":["Default Title"]}],"images":[{"id":3883615715394,"product_id":1462571040834,"position":1,"created_at":"2018-07-20T14:15:00-05:00","updated_at":"2019-10-21T23:50:09-05:00","alt":null,"width":4272,"height":2848,"src":"https:\/\/cdn.shopify.com\/s\/files\/1\/0027\/8770\/4898\/products\/c7da2f4a513ab86824be5e5eab31c2bb.jpg?v=1571719809","variant_ids":[]}],"image":{"id":3883615715394,"product_id":1462571040834,"position":1,"created_at":"2018-07-20T14:15:00-05:00","updated_at":"2019-10-21T23:50:09-05:00","alt":null,"width":4272,"height":2848,"src":"https:\/\/cdn.shopify.com\/s\/files\/1\/0027\/8770\/4898\/products\/c7da2f4a513ab86824be5e5eab31c2bb.jpg?v=1571719809","variant_ids":[]}}}