{"product":{"id":7366268977338,"title":"Weatherstrip - Rear Hatch \/ Liftgate  Lower Seal - FJ60, FJ62 1981-1990","body_html":"\u003cp\u003eThis weatherstrip is an exact reproduction for the FJ60 and FJ62 lower tailgate \/ rear hatch\u003c\/p\u003e\n\u003cp\u003eFits: FJ60 and FJ62s as well as all 60 series with rear hatches\u003c\/p\u003e","vendor":"Cruiser Corps","product_type":"Weatherstrip","created_at":"2023-04-20T15:52:40-05:00","handle":"rear-tail-gate-weatherstrip-seal-1981-1990","updated_at":"2023-10-02T18:06:34-05:00","published_at":"2023-04-20T15:52:40-05:00","template_suffix":"","published_scope":"web","tags":"1981, 1982, 1983, 1984, 1985, 1986, 1987, 1988, 1989, 1990, 60 Series, BJ60, BJ61, FJ60, FJ61, FJ62, Gaskets, Hatch, Seals, weatherstrip","variants":[{"id":42405719343290,"product_id":7366268977338,"title":"Default Title","price":"84.95","sku":"522-108","position":1,"compare_at_price":"","fulfillment_service":"manual","inventory_management":"shopify","option1":"Default Title","option2":null,"option3":null,"created_at":"2023-04-20T15:52:40-05:00","updated_at":"2023-10-02T18:06:34-05:00","taxable":true,"barcode":"337247185","grams":454,"image_id":null,"weight":1.0,"weight_unit":"lb","tax_code":"","requires_shipping":true,"quantity_rule":{"min":1,"max":null,"increment":1},"quantity_price_breaks":[]}],"options":[{"id":9420931399866,"product_id":7366268977338,"name":"Title","position":1,"values":["Default Title"]}],"images":[{"id":33141157200058,"product_id":7366268977338,"position":1,"created_at":"2023-04-20T15:54:50-05:00","updated_at":"2023-04-20T15:54:51-05:00","alt":null,"width":1608,"height":1608,"src":"https:\/\/cdn.shopify.com\/s\/files\/1\/0027\/8770\/4898\/products\/Six.png?v=1682024091","variant_ids":[]},{"id":33141157265594,"product_id":7366268977338,"position":2,"created_at":"2023-04-20T15:54:57-05:00","updated_at":"2023-04-20T15:54:58-05:00","alt":null,"width":1427,"height":1428,"src":"https:\/\/cdn.shopify.com\/s\/files\/1\/0027\/8770\/4898\/products\/Three.png?v=1682024098","variant_ids":[]},{"id":33141157298362,"product_id":7366268977338,"position":3,"created_at":"2023-04-20T15:55:03-05:00","updated_at":"2023-04-20T15:55:04-05:00","alt":null,"width":2232,"height":2232,"src":"https:\/\/cdn.shopify.com\/s\/files\/1\/0027\/8770\/4898\/products\/Two.jpg?v=1682024104","variant_ids":[]}],"image":{"id":33141157200058,"product_id":7366268977338,"position":1,"created_at":"2023-04-20T15:54:50-05:00","updated_at":"2023-04-20T15:54:51-05:00","alt":null,"width":1608,"height":1608,"src":"https:\/\/cdn.shopify.com\/s\/files\/1\/0027\/8770\/4898\/products\/Six.png?v=1682024091","variant_ids":[]}}}